philips_hue_midi/__init__.py
philips_hue_midi/config.py
philips_hue_midi/constants.py
philips_hue_midi/event.py
philips_hue_midi/main.py
philips_hue_midi/rgbxy.py
philips_hue_midi/utils.py
philips_hue_midi/controllers/__init__.py
philips_hue_midi/controllers/note_controller.py
philips_hue_midi/controllers/register_controller.py
philips_hue_midi/controllers/router.py
philips_hue_midi/core/__init__.py
philips_hue_midi/core/base_controller.py
philips_hue_midi/core/channel.py
philips_hue_midi-2.1.4.dist-info/licenses/LICENSE
philips_hue_midi-2.1.4.dist-info/METADATA
philips_hue_midi-2.1.4.dist-info/WHEEL
philips_hue_midi-2.1.4.dist-info/entry_points.txt
philips_hue_midi-2.1.4.dist-info/top_level.txt
philips_hue_midi-2.1.4.dist-info/RECORD
