Metadata-Version: 2.4
Name: philips-hue-midi
Version: 2.1.4
Summary: A program that allows controlling Philips Hue lights using a midi keyboard.
Author-email: Aru <arunorth@gmail.com>
Requires-Python: >=3.13
License-File: LICENSE
Requires-Dist: fire>=0.7.0
Requires-Dist: mido>=1.3.3
Requires-Dist: phue>=1.1
Requires-Dist: python-rtmidi>=1.5.8
Requires-Dist: requests>=2.32.3
Requires-Dist: rich>=14.0.0
Dynamic: license-file
